ezra/__init__.py
ezra/conceptnet_strategy.py
ezra/lang.py
ezra/search.py
ezra/resources/__init__.py
ezra/resources/abbr.py
ezra/resources/bible.py
ezra/resources/build_db.py
ezra/resources/conceptnet_strategy.pickle
ezra/resources/db.h5
ezra/resources/db.py
ezra/static/favicon.svg
ezra/static/google61ad13e8b605dad5.html
ezra/static/robot.txt
ezra/static/script.js
ezra/static/api/favicon-16x16.png
ezra/static/api/favicon-32x32.png
ezra/static/api/index.html
ezra/static/api/openapi.yaml
ezra/static/api/redirect.html
ezra/static/api/swagger-ui-bundle.js
ezra/static/api/swagger-ui-standalone-preset.js
ezra/static/api/swagger-ui.css
ezra/static/css/all.min.css
ezra/static/css/cover.css
ezra/static/css/style.css
ezra/static/webfonts/fa-brands-400.eot
ezra/static/webfonts/fa-brands-400.svg
ezra/static/webfonts/fa-brands-400.ttf
ezra/static/webfonts/fa-brands-400.woff
ezra/static/webfonts/fa-brands-400.woff2
ezra/static/webfonts/fa-regular-400.eot
ezra/static/webfonts/fa-regular-400.svg
ezra/static/webfonts/fa-regular-400.ttf
ezra/static/webfonts/fa-regular-400.woff
ezra/static/webfonts/fa-regular-400.woff2
ezra/static/webfonts/fa-solid-900.eot
ezra/static/webfonts/fa-solid-900.svg
ezra/static/webfonts/fa-solid-900.ttf
ezra/static/webfonts/fa-solid-900.woff
ezra/static/webfonts/fa-solid-900.woff2
ezra/templates/base.html
ezra/templates/index.html
ezra/templates/search.html
ezra/word_tokenizer/__init__.py
ezra/word_tokenizer/classics.txt
ezra/word_tokenizer/names.txt
ezra_search-0.9.0.dist-info/LICENSE
ezra_search-0.9.0.dist-info/METADATA
ezra_search-0.9.0.dist-info/WHEEL
ezra_search-0.9.0.dist-info/top_level.txt
ezra_search-0.9.0.dist-info/RECORD
