Metadata-Version: 2.1
Name: ezra-search
Version: 0.9.0
Summary: Semantic Search Engine for Chinese Bible
Home-page: https://ezra-bible-search.df.r.appspot.com/
Author: Ken Hung
Author-email: eiekenhung@gmail.com
License: AGPLv3
Project-URL: Repository, https://github.com/KenHung/ezra-bible-search/
Project-URL: Documentation, https://github.com/KenHung/ezra-bible-search/wiki
Keywords: Bible,search
Platform: UNKNOWN
Classifier: Programming Language :: Python :: 3
Classifier: License :: OSI Approved :: GNU Affero General Public License v3
Classifier: Operating System :: OS Independent
Requires-Python: >=3.8
License-File: LICENSE
Requires-Dist: Flask
Requires-Dist: tables
Requires-Dist: OpenCC (>=1.1.3)
Requires-Dist: jieba
